lara_queue/__init__.py
lara_queue/async_connection.py
lara_queue/async_metrics_collector.py
lara_queue/async_queue.py
lara_queue/base_queue.py
lara_queue/connection.py
lara_queue/metrics_collector.py
lara_queue/queue.py
lara_queue/retry_strategy.py
lara_queue/module/phpserialize.py
laraqueue-1.2.0.dist-info/licenses/LICENSE
laraqueue-1.2.0.dist-info/METADATA
laraqueue-1.2.0.dist-info/WHEEL
laraqueue-1.2.0.dist-info/top_level.txt
laraqueue-1.2.0.dist-info/RECORD
