Metadata-Version: 2.4
Name: LaraQueue
Version: 1.2.0
Summary: Simple and lightweight queue synchronization between Python and Laravel using Redis with Horizon support
Author: Anton Mashkovtsev
Author-email: Mashkovtsev Anton <mashkovtsev@protonmail.com>
License: MIT
Project-URL: Homepage, https://github.com/bat0n/lara-queue
Project-URL: Repository, https://github.com/bat0n/lara-queue
Project-URL: Documentation, https://github.com/bat0n/lara-queue#readme
Project-URL: Bug Tracker, https://github.com/bat0n/lara-queue/issues
Keywords: laravel,queue,redis,python,job,worker
Classifier: Development Status :: 4 - Beta
Classifier: Intended Audience :: Developers
Classifier: License :: OSI Approved :: MIT License
Classifier: Operating System :: OS Independent
Classifier: Programming Language :: Python :: 3
Classifier: Programming Language :: Python :: 3.7
Classifier: Programming Language :: Python :: 3.8
Classifier: Programming Language :: Python :: 3.9
Classifier: Programming Language :: Python :: 3.10
Classifier: Programming Language :: Python :: 3.11
Classifier: Topic :: Software Development :: Libraries :: Python Modules
Classifier: Topic :: System :: Distributed Computing
Requires-Python: >=3.7
License-File: LICENSE
Requires-Dist: redis>=4.0.0
Requires-Dist: pyee>=8.0.0
Requires-Dist: aioredis>=2.0.0
Provides-Extra: dev
Requires-Dist: pytest>=6.0; extra == "dev"
Requires-Dist: pytest-mock>=3.0; extra == "dev"
Requires-Dist: black>=21.0; extra == "dev"
Requires-Dist: flake8>=3.8; extra == "dev"
Requires-Dist: mypy>=0.800; extra == "dev"
Dynamic: license-file
